AUTHORS
COPYING
MANIFEST.in
README.rst
changelog.rst
requirements.txt
setup.py
ufp/__init__.py
ufp/bs4.py
ufp/cipher.py
ufp/dict.py
ufp/html.py
ufp/image.py
ufp/list.py
ufp/logging.py
ufp/math.py
ufp/path.py
ufp/pdf.py
ufp/process.py
ufp/random.py
ufp/repr.py
ufp/shell.py
ufp/string.py
ufp/ufp.py
ufp/web.py
ufp.egg-info/PKG-INFO
ufp.egg-info/SOURCES.txt
ufp.egg-info/dependency_links.txt
ufp.egg-info/not-zip-safe
ufp.egg-info/requires.txt
ufp.egg-info/top_level.txt
ufp/_compatibleness/__init__.py
ufp/_compatibleness/image.py
ufp/_compatibleness/ufp.py
ufp/_compatibleness/terminal/__init__.py
ufp/_compatibleness/terminal/color/__init__.py
ufp/_compatibleness/terminal/color/bak.py
ufp/_compatibleness/terminal/color/color.py
ufp/gui/__init__.py
ufp/gui/notepad.py
ufp/gui/pulse_progress.py
ufp/terminal/__init__.py
ufp/terminal/debug.py
ufp/terminal/terminal.py