Metadata-Version: 1.1
Name: ufp
Version: 1.14
Summary: ufp 라이브러리 python 버전. 각종, 편리한 함수들의 모음.
Home-page: http://thestars3.tistory.com/
Author: 별님
Author-email: w7dn1ng75r@gmail.com
License: GPL v3
Download-URL: https://github.com/Thestars3/pyufp/releases
Keywords: path,web,html,string,image,gui,termianl
Platform: Unix
Platform: POSIX
Platform: MacOS
Classifier: Programming Language :: Python :: 2.7
Classifier: Programming Language :: Python :: 2 :: Only
Classifier: Intended Audience :: Developers
Classifier: Development Status :: 5 - Production/Stable
Classifier: Environment :: X11 Applications
Classifier: Environment :: Console
Classifier: Topic :: Terminals :: Terminal Emulators/X Terminals
Classifier: Topic :: System :: Shells
Classifier: Topic :: Utilities
Classifier: Topic :: Text Processing :: General
Classifier: Topic :: Software Development :: Libraries :: Python Modules
Classifier: Operating System :: Unix
Classifier: Operating System :: POSIX
Classifier: Operating System :: MacOS
Classifier: License :: OSI Approved :: GNU General Public License v3 (GPLv3)
